config/__init__.py
config/conftest.py
PytestGetInterfaceInfoPlugin-1.0.5.dist-info/METADATA
PytestGetInterfaceInfoPlugin-1.0.5.dist-info/WHEEL
PytestGetInterfaceInfoPlugin-1.0.5.dist-info/top_level.txt
PytestGetInterfaceInfoPlugin-1.0.5.dist-info/RECORD
