Metadata-Version: 2.1
Name: PytestGetInterfaceInfoPlugin
Version: 1.0.5
Summary: Get executed interface information in pytest interface automation framework
Requires-Dist: pytest
